aclib/pip/__init__.py
aclib/pip/__main__.py
aclib/pip/__API__/colorstr.py
aclib/pip/__API__/distribution.py
aclib/pip/__API__/libmanager.py
aclib.pip-0.0.1.dist-info/LICENSE
aclib.pip-0.0.1.dist-info/METADATA
aclib.pip-0.0.1.dist-info/WHEEL
aclib.pip-0.0.1.dist-info/entry_points.txt
aclib.pip-0.0.1.dist-info/top_level.txt
aclib.pip-0.0.1.dist-info/RECORD
